pysigview/__init__.py
pysigview/app/__init__.py
pysigview/app/main_window.py
pysigview/app/start.py
pysigview/cameras/__init__.py
pysigview/cameras/navigation.py
pysigview/cameras/signal_camera.py
pysigview/config/__init__.py
pysigview/config/base.py
pysigview/config/main.py
pysigview/config/system.py
pysigview/config/user.py
pysigview/config/utils.py
pysigview/core/__init__.py
pysigview/core/buffer_handler.py
pysigview/core/multiringbuffer.py
pysigview/core/plot_transform.py
pysigview/core/pysigviewmultiringbuffer.py
pysigview/core/source_manager.py
pysigview/core/thread_workers.py
pysigview/core/visual_container.py
pysigview/core/clients/__init__.py
pysigview/core/clients/clients.py
pysigview/core/clients/pysigview.py
pysigview/core/file_formats/__init__.py
pysigview/core/file_formats/d.py
pysigview/core/file_formats/formats.py
pysigview/core/file_formats/mefd.py
pysigview/images/SPLASH.png
pysigview/images/autoscale.svg
pysigview/images/camera.svg
pysigview/images/circle.svg
pysigview/images/database.svg
pysigview/images/database2.svg
pysigview/images/database_down.svg
pysigview/images/database_up.svg
pysigview/images/file.svg
pysigview/images/floppy-disk.svg
pysigview/images/grid.svg
pysigview/images/play.svg
pysigview/images/plus.svg
pysigview/images/pysigview.svg
pysigview/images/reload.svg
pysigview/images/spreadsheet.svg
pysigview/plugins/__init__.py
pysigview/plugins/annotations.py
pysigview/plugins/base.py
pysigview/plugins/channels.py
pysigview/plugins/console.py
pysigview/plugins/console_embed.py
pysigview/plugins/database.py
pysigview/plugins/measurement.py
pysigview/plugins/navigation_bar.py
pysigview/plugins/plugin.py
pysigview/plugins/transforms.py
pysigview/plugins/annotation_formats/__init__.py
pysigview/plugins/annotation_formats/formats.py
pysigview/utils/__init__.py
pysigview/utils/qthelpers.py
pysigview/visuals/__init__.py
pysigview/visuals/crosshair_visual.py
pysigview-0.0a9.dist-info/DESCRIPTION.rst
pysigview-0.0a9.dist-info/METADATA
pysigview-0.0a9.dist-info/RECORD
pysigview-0.0a9.dist-info/WHEEL
pysigview-0.0a9.dist-info/entry_points.txt
pysigview-0.0a9.dist-info/metadata.json
pysigview-0.0a9.dist-info/top_level.txt
