Metadata-Version: 2.0
Name: pysigview
Version: 0.0a9
Summary: Package for viewing signals using VisPy
Home-page: https://github.com/ICRC-BME/PySigView
Author: Jan Cimbalnik
Author-email: jan.cimbalnik@fnusa.cz,jan.cimbalnik@mayo.edu
License: Apache 2.0
Keywords: PyQt5 vispy signal
Platform: Linux
Platform: MacOS
Classifier: License :: OSI Approved :: MIT License
Classifier: Operating System :: MacOS
Classifier: Operating System :: POSIX :: Linux
Classifier: Operating System :: Microsoft :: Windows
Classifier: Programming Language :: Python :: 3
Classifier: Development Status :: 3 - Alpha
Classifier: Topic :: Scientific/Engineering
Requires-Dist: pyqt5 (<5.10)
Requires-Dist: numpy
Requires-Dist: vispy
Requires-Dist: pyopengl
Requires-Dist: pandas
Requires-Dist: scipy
Requires-Dist: bcolz
Requires-Dist: sqlalchemy
Requires-Dist: pymysql
Requires-Dist: pysigview-cs
Requires-Dist: pillow
Requires-Dist: jupyter
Requires-Dist: pymef (>=0.2)
Requires-Dist: pydread
